pattern_kit/__init__.py
pattern_kit/architectural/service_locator.py
pattern_kit/behavioral/__init__.py
pattern_kit/behavioral/event.py
pattern_kit/behavioral/event_emitter.py
pattern_kit/behavioral/handler_pipeline.py
pattern_kit/behavioral/observer.py
pattern_kit/creational/factory.py
pattern_kit/creational/object_pool.py
pattern_kit/creational/singleton.py
pattern_kit/structural/delegate_mixin.py
pattern_kit/utils/config_loader.py
pattern_kit-1.3.0.dist-info/licenses/LICENSE.txt
pattern_kit-1.3.0.dist-info/METADATA
pattern_kit-1.3.0.dist-info/WHEEL
pattern_kit-1.3.0.dist-info/top_level.txt
pattern_kit-1.3.0.dist-info/RECORD
