Metadata-Version: 2.4
Name: pattern_kit
Version: 1.3.0
Summary: A modern Python library of reusable software design patterns.
Author-email: Mickael Burguet <bash88@email.com>
License: MIT
Project-URL: Homepage, https://github.com/rundef/pattern_kit
Project-URL: Repository, https://github.com/rundef/pattern_kit
Project-URL: Issues, https://github.com/rundef/pattern_kit/issues
Project-URL: Documentation, https://pattern-kit.readthedocs.io/en/latest/
Keywords: python,design patterns,software architecture,singleton,factory,object pool,observer,event emitter,pipeline,service locator,creational patterns,behavioral patterns,architectural patterns,developer tools,pattern library
Classifier: Development Status :: 5 - Production/Stable
Classifier: Programming Language :: Python :: 3
Classifier: Programming Language :: Python :: 3.10
Classifier: Programming Language :: Python :: 3.11
Classifier: Programming Language :: Python :: 3.12
Classifier: Programming Language :: Python :: 3.13
Classifier: License :: OSI Approved :: MIT License
Classifier: Intended Audience :: Developers
Classifier: Topic :: Software Development :: Libraries
Classifier: Topic :: Software Development :: Code Generators
Requires-Python: >=3.10
License-File: LICENSE.txt
Dynamic: license-file
